rain_orm/__init__.py
rain_orm/common.py
rain_orm/db.py
rain_orm/metatable.py
rain_orm/table.py
rain_orm/column/__init__.py
rain_orm/column/base.py
rain_orm/column/date.py
rain_orm/column/number.py
rain_orm/column/string.py
rain_orm/error/__init__.py
rain_orm/error/error.py
rain_orm/sql_builder/__init__.py
rain_orm/sql_builder/ddl_builder.py
rain_orm/sql_builder/dmldql_builder.py
tests/__init__.py
tests/t.py
rain_orm-1.0.9.dist-info/LICENSE
rain_orm-1.0.9.dist-info/METADATA
rain_orm-1.0.9.dist-info/WHEEL
rain_orm-1.0.9.dist-info/top_level.txt
rain_orm-1.0.9.dist-info/RECORD
