Metadata-Version: 2.1
Name: rain-orm
Version: 1.0.9
Summary: a tiny orm frame
Home-page: https://github.com/cgynb/rain-orm
Author: rain
Author-email: 948628463@qq.com
License: UNKNOWN
Platform: UNKNOWN
License-File: LICENSE
Requires-Dist: pymysql (==1.0.3)
